[
  {
    "title": "引言：视听语言与剪辑的重要性",
    "length": 2500,
    "level": 1
  },
  {
    "title": "电影视听语言的构成元素：画面、声音、运动",
    "length": 3500,
    "level": 1
  },
  {
    "title": "镜头景别：远景、全景、中景、近景、特写",
    "length": 3200,
    "level": 1
  },
  {
    "title": "镜头角度：平视、仰视、俯视、倾斜角度",
    "length": 3000,
    "level": 1
  },
  {
    "title": "色彩在电影中的运用：色彩心理学与色彩象征",
    "length": 3300,
    "level": 1
  },
  {
    "title": "运动摄影：推、拉、摇、移、跟镜头",
    "length": 3100,
    "level": 1
  },
  {
    "title": "声音元素：对白、音效、音乐、同期声与后期配音",
    "length": 3400,
    "level": 1
  },
  {
    "title": "电影蒙太奇：定义、类型与叙事功能",
    "length": 3600,
    "level": 1
  },
  {
    "title": "剪辑的参考原则：连贯性、节奏、强调",
    "length": 3200,
    "level": 1
  },
  {
    "title": "数字电影剪辑技术概述：非线性剪辑的优势",
    "length": 2800,
    "level": 1
  },
  {
    "title": "Final Cut Pro X 软件简介与界面操作",
    "length": 3000,
    "level": 1
  },
  {
    "title": "剪辑前的准备工作：素材管理、项目设置",
    "length": 2900,
    "level": 1
  },
  {
    "title": "建立与打开 Final Cut Pro X 剪辑项目文件",
    "length": 2700,
    "level": 1
  },
  {
    "title": "基本剪辑操作：导入素材、时间线操作、粗剪",
    "length": 3500,
    "level": 1
  },
  {
    "title": "剪辑点的选择与画面组接技巧",
    "length": 3300,
    "level": 1
  },
  {
    "title": "高级剪辑技巧：转场、特效、字幕添加",
    "length": 3600,
    "level": 1
  },
  {
    "title": "音频剪辑与混音基础：音轨调整、音效处理",
    "length": 3400,
    "level": 1
  },
  {
    "title": "多机位剪辑：原理与 Final Cut Pro X 应用",
    "length": 3200,
    "level": 1
  },
  {
    "title": "剪辑流程优化与效率提升技巧",
    "length": 3000,
    "level": 1
  },
  {
    "title": "输出与备份：Final Cut Pro X 项目的导出与存档",
    "length": 2800,
    "level": 1
  },
  {
    "title": "数字校色技术概述：色彩校正与风格化",
    "length": 2900,
    "level": 1
  },
  {
    "title": "Color 软件应用：界面、工具与基本操作",
    "length": 3100,
    "level": 1
  },
  {
    "title": "Color 色彩校正流程：一级校色与二级校色",
    "length": 3300,
    "level": 1
  },
  {
    "title": "Color 风格化调色：预设与自定义风格创建",
    "length": 3200,
    "level": 1
  },
  {
    "title": "达芬奇 Resolve 软件简介与工作流程",
    "length": 3000,
    "level": 1
  },
  {
    "title": "达芬奇 Resolve 界面与基础工具操作",
    "length": 3100,
    "level": 1
  },
  {
    "title": "达芬奇 Resolve 色彩管理与节点系统",
    "length": 3400,
    "level": 1
  },
  {
    "title": "达芬奇 Resolve 色彩校正实战：不同场景的调色技巧",
    "length": 3500,
    "level": 1
  },
  {
    "title": "达芬奇 Resolve 风格化调色与高级技巧",
    "length": 3300,
    "level": 1
  },
  {
    "title": "剪辑与校色的协同工作流程：从剪辑到后期制作",
    "length": 3200,
    "level": 1
  },
  {
    "title": "视听语言与剪辑的未来发展趋势：新技术与新应用",
    "length": 3000,
    "level": 1
  },
  {
    "title": "结论：视听语言与剪辑在电影创作中的核心价值",
    "length": 2000,
    "level": 1
  }
]